setup.cfg
setup.py
namealizer/__init__.py
namealizer/namealizer.py
namealizer/test_namealizer.py
namealizer.egg-info/PKG-INFO
namealizer.egg-info/SOURCES.txt
namealizer.egg-info/dependency_links.txt
namealizer.egg-info/top_level.txt
namealizer/dictionaries/all_en_US.dict
scripts/namealizer