Metadata-Version: 1.1
Name: namealizer
Version: 0.6
Summary: A tool for generating and formatting random words
Home-page: https://github.com/LeonardMH/namealizer
Author: Michael Leonard
Author-email: maybeillrememberit@gmail.com
License: UNKNOWN
Download-URL: https://github.com/LeonardMH/namealizer/tarball/0.6
Keywords: random words,namealizer,word,dictionary
Platform: UNKNOWN
Classifier: Development Status :: 4 - Beta
Classifier: Environment :: Console
Classifier: Intended Audience :: Developers
Classifier: License :: OSI Approved :: MIT License
Classifier: Operating System :: MacOS :: MacOS X
Classifier: Operating System :: Microsoft :: Windows
Classifier: Operating System :: POSIX
Classifier: Programming Language :: Python
Classifier: Topic :: Utilities
